<?xml version="1.0"?>
<CarDesign numParts="47">
  <Chassis def="Cabin_Moonwalker" pos="0.000 0.750 -1.800">
    <Part def="CarPart_PowerGiver_epic" weld_pos="0.000 1.350 -0.300" weld_rot_idx="22" dye="Dye_Khaki03" />
    <Part def="CarPart_Military_box_4x1x8" weld_pos="0.000 1.050 -3.300" weld_rot_idx="8" dye="Dye_Khaki03" />
    <Part def="CarPart_Military_slope_thin_1x1x4" weld_pos="-0.600 0.300 -3.000" weld_rot_idx="13" dye="Dye_Khaki03" />
    <Part def="CarPart_Military_slope_thin_1x1x4" weld_pos="0.600 0.300 -3.000" weld_rot_idx="13" dye="Dye_Khaki03" />
    <Part def="CarPart_ChassisTruck6" weld_pos="0.000 0.750 -2.400" dye="Dye_Khaki03" />
    <Part def="CarPart_Military_box_slope_4x1x8" weld_pos="0.000 1.350 0.000" weld_rot_idx="12" dye="Dye_Khaki03" />
    <Part def="CarPart_Military_slope_dble_2x1x4" weld_pos="-0.900 1.050 -3.300" weld_rot_idx="7" dye="Dye_Grey03" />
    <Part def="CarPart_Exhaust2" weld_pos="1.200 0.900 -0.450" dye="Dye_Grey03" />
    <Part def="CarPart_Exhaust2" weld_pos="1.200 0.900 -0.150" dye="Dye_Grey03" />
    <Part def="CarPart_Grid_1" weld_pos="1.200 1.350 -0.300" weld_rot_idx="11" dye="Dye_Khaki03" />
    <Part def="CarPart_Bag03" weld_pos="-1.200 1.500 -0.750" weld_rot_idx="21" dye="Dye_Grey03" />
    <Part def="CarPart_Headlights4" weld_pos="0.000 1.350 -3.300" dye="Dye_Grey03" />
    <Part def="CarPart_WheelMilitary_S" weld_pos="-0.750 0.450 -2.700" dye="Dye_Grey03" />
    <Part def="CarPart_WheelMilitary_S" weld_pos="0.750 0.450 -2.700" weld_rot_idx="4" dye="Dye_Grey03" />
    <Part def="CarPart_Muscle_fender" weld_pos="1.350 1.050 -2.700" dye="Dye_Khaki03" />
    <Part def="CarPart_Muscle_fender" weld_pos="-1.350 1.050 -2.700" weld_rot_idx="4" dye="Dye_Khaki03" />
    <Part def="CarPart_Brace" weld_pos="-1.200 1.650 -1.200" weld_rot_idx="17" dye="Dye_Grey03" />
    <Part def="CarPart_Brace" weld_pos="1.200 1.650 -1.200" weld_rot_idx="20" dye="Dye_Grey03" />
    <Part def="CarPart_ChassisTruck6" weld_pos="0.000 0.750 0.000" />
    <Part def="CarPart_ChassisTruck6" weld_pos="0.000 0.750 -1.200" />
    <Part def="CarPart_ChassisBase4" weld_pos="0.000 0.750 1.200" />
    <Part def="CarPart_AviaRadial2x2x2" weld_pos="-0.900 0.750 -1.500" weld_rot_idx="22" />
    <Part def="CarPart_AviaRadial2x2x2" weld_pos="-0.900 0.750 -0.900" />
    <Part def="CarPart_AviaRadial2x2x2" weld_pos="0.900 0.750 -1.500" weld_rot_idx="22" />
    <Part def="CarPart_AviaRadial2x2x2" weld_pos="0.900 0.750 -0.900" weld_rot_idx="4" />
    <Part def="CarPart_Grid_1" weld_pos="-1.200 1.350 -0.300" weld_rot_idx="10" dye="Dye_Khaki03" />
    <Part def="CarPart_Bag03" weld_pos="-1.200 1.500 -0.450" weld_rot_idx="21" dye="Dye_Grey03" />
    <Part def="CarPart_Buggy_bumper" weld_pos="0.000 0.750 -3.600" />
    <Part def="CarPart_WheelDouble_R_epic" weld_pos="-0.450 0.450 1.200" />
    <Part def="CarPart_WheelDouble_R_epic" weld_pos="0.450 0.450 1.200" weld_rot_idx="4" />
    <Part def="CarPart_Muscle_back" weld_pos="0.000 0.750 1.950" />
    <Part def="CarPart_Holder_4x3_rare" weld_pos="0.450 1.050 1.200" weld_rot_idx="2" />
    <Part def="CarPart_Holder_4x3_rare" weld_pos="-0.450 1.050 1.200" weld_rot_idx="2" />
    <Part def="CarPart_Buggy_Grid4" weld_pos="0.000 1.650 0.300" weld_rot_idx="6" />
    <Part def="CarPart_Grid_1" weld_pos="0.000 1.950 0.000" />
    <Part def="CarPart_Grid_3" weld_pos="0.000 2.250 -0.600" weld_rot_idx="5" />
    <Part def="CarPart_Gun_Machinegun" weld_pos="0.900 1.650 -3.300" weaponGroup="1" />
    <Part def="CarPart_Gun_Machinegun" weld_pos="-0.900 1.650 -3.300" weaponGroup="1" />
    <Part def="CarPart_Military_slope_dble_2x1x4" weld_pos="0.900 1.050 -3.300" weld_rot_idx="7" dye="Dye_Grey03" />
    <Part def="CarPart_EngineMini_rare" weld_pos="0.000 1.050 1.200" />
    <Part def="CarPart_Brakelights1" weld_pos="0.900 1.950 0.300" weld_rot_idx="1" />
    <Part def="CarPart_Brakelights1" weld_pos="-0.900 1.950 0.300" weld_rot_idx="1" />
    <Part def="CarPart_FenderSolidOutside_rare" weld_pos="0.600 0.750 1.200" />
    <Part def="CarPart_FenderSolidOutside_rare" weld_pos="-0.600 0.750 1.200" weld_rot_idx="4" />
    <Part def="CarPart_Footstep" weld_pos="0.900 0.600 -0.900" weld_rot_idx="23" />
    <Part def="CarPart_Footstep" weld_pos="-0.900 0.600 -0.900" weld_rot_idx="19" />
    <Part def="CarPart_Gun_Syfy_Plazma" weld_pos="0.000 2.250 0.000" weaponGroup="2" />
  </Chassis>
</CarDesign>
